ice_moviepy/Clip.py
ice_moviepy/__init__.py
ice_moviepy/compat.py
ice_moviepy/config.py
ice_moviepy/config_defaults.py
ice_moviepy/decorators.py
ice_moviepy/editor.py
ice_moviepy/tools.py
ice_moviepy/utils.py
ice_moviepy/version.py
ice_moviepy/audio/AudioClip.py
ice_moviepy/audio/__init__.py
ice_moviepy/audio/fx/__init__.py
ice_moviepy/audio/fx/audio_fadein.py
ice_moviepy/audio/fx/audio_fadeout.py
ice_moviepy/audio/fx/audio_left_right.py
ice_moviepy/audio/fx/audio_loop.py
ice_moviepy/audio/fx/audio_normalize.py
ice_moviepy/audio/fx/volumex.py
ice_moviepy/audio/fx/all/__init__.py
ice_moviepy/audio/io/AudioFileClip.py
ice_moviepy/audio/io/__init__.py
ice_moviepy/audio/io/ffmpeg_audiowriter.py
ice_moviepy/audio/io/preview.py
ice_moviepy/audio/io/readers.py
ice_moviepy/audio/tools/__init__.py
ice_moviepy/audio/tools/cuts.py
ice_moviepy/video/VideoClip.py
ice_moviepy/video/VideoCutSubtitle.py
ice_moviepy/video/__init__.py
ice_moviepy/video/compositing/CompositeVideoClip.py
ice_moviepy/video/compositing/__init__.py
ice_moviepy/video/compositing/concatenate.py
ice_moviepy/video/compositing/on_color.py
ice_moviepy/video/compositing/positioning.py
ice_moviepy/video/compositing/transitions.py
ice_moviepy/video/fx/__init__.py
ice_moviepy/video/fx/accel_decel.py
ice_moviepy/video/fx/blackwhite.py
ice_moviepy/video/fx/blink.py
ice_moviepy/video/fx/colorx.py
ice_moviepy/video/fx/crop.py
ice_moviepy/video/fx/even_size.py
ice_moviepy/video/fx/fadein.py
ice_moviepy/video/fx/fadeout.py
ice_moviepy/video/fx/freeze.py
ice_moviepy/video/fx/freeze_region.py
ice_moviepy/video/fx/gamma_corr.py
ice_moviepy/video/fx/headblur.py
ice_moviepy/video/fx/invert_colors.py
ice_moviepy/video/fx/loop.py
ice_moviepy/video/fx/lum_contrast.py
ice_moviepy/video/fx/make_loopable.py
ice_moviepy/video/fx/margin.py
ice_moviepy/video/fx/mask_and.py
ice_moviepy/video/fx/mask_color.py
ice_moviepy/video/fx/mask_or.py
ice_moviepy/video/fx/mirror_x.py
ice_moviepy/video/fx/mirror_y.py
ice_moviepy-0.0.9.dist-info/LICENSE
ice_moviepy-0.0.9.dist-info/METADATA
ice_moviepy-0.0.9.dist-info/WHEEL
ice_moviepy-0.0.9.dist-info/top_level.txt
ice_moviepy-0.0.9.dist-info/RECORD
